named_decorator.py
named_decorator-0.2.0.dist-info/LICENSE.txt
named_decorator-0.2.0.dist-info/METADATA
named_decorator-0.2.0.dist-info/WHEEL
named_decorator-0.2.0.dist-info/top_level.txt
named_decorator-0.2.0.dist-info/RECORD
